LICENSE
MANIFEST.in
README.md
setup.py
ideal_categories_django/__init__.py
ideal_categories_django/admin.py
ideal_categories_django/apps.py
ideal_categories_django/models.py
ideal_categories_django/serializers.py
ideal_categories_django/tests.py
ideal_categories_django/urls.py
ideal_categories_django/views.py
ideal_categories_django.egg-info/PKG-INFO
ideal_categories_django.egg-info/SOURCES.txt
ideal_categories_django.egg-info/dependency_links.txt
ideal_categories_django.egg-info/requires.txt
ideal_categories_django.egg-info/top_level.txt
ideal_categories_django/migrations/__init__.py