Metadata-Version: 2.2
Name: ideal-categories-django
Version: 0.1
Summary: A Django REST framework package for managing categories and subcategories.
Home-page: https://github.com/prashantidealittechno/ideal-categories-django
Author: Prashant IdealITTechno
Author-email: prashant.idealittechno@gmail.com
License: MIT
Classifier: Development Status :: 3 - Alpha
Classifier: Framework :: Django
Classifier: Intended Audience :: Developers
Classifier: License :: OSI Approved :: MIT License
Classifier: Programming Language :: Python :: 3
Classifier: Programming Language :: Python :: 3.6
Classifier: Programming Language :: Python :: 3.7
Classifier: Programming Language :: Python :: 3.8
Classifier: Programming Language :: Python :: 3.9
License-File: LICENSE
Requires-Dist: Django>=3.2
Requires-Dist: djangorestframework>=3.12
Dynamic: author
Dynamic: author-email
Dynamic: classifier
Dynamic: description
Dynamic: description-content-type
Dynamic: home-page
Dynamic: license
Dynamic: requires-dist
Dynamic: summary
